ml_tracking/__init__.py
ml_tracking/api_client.py
ml_tracking/configuration.py
ml_tracking/exceptions.py
ml_tracking/model_utils.py
ml_tracking/rest.py
ml_tracking/api/__init__.py
ml_tracking/api/data_rows_api.py
ml_tracking/api/delete_api.py
ml_tracking/api/download_api.py
ml_tracking/api/epoch_info_api.py
ml_tracking/api/hosted_service_api.py
ml_tracking/api/ml_model_api.py
ml_tracking/api/model_api.py
ml_tracking/api/report_api.py
ml_tracking/api/session_api.py
ml_tracking/apis/__init__.py
ml_tracking/model/__init__.py
ml_tracking/model/data_row_dto.py
ml_tracking/model/data_row_image_dto.py
ml_tracking/model/entity.py
ml_tracking/model/epoch_info.py
ml_tracking/model/epoch_info_all_of.py
ml_tracking/model/epoch_update_command.py
ml_tracking/model/hosted_service_dto.py
ml_tracking/model/image_dto.py
ml_tracking/model/iteration_update_command.py
ml_tracking/model/model.py
ml_tracking/model/model_all_of.py
ml_tracking/model/paginated_list_of_data_row_dto.py
ml_tracking/model/register_model_run_command.py
ml_tracking/model/row_type.py
ml_tracking/model/save_notebook_code_command.py
ml_tracking/model/session.py
ml_tracking/model/session_all_of.py
ml_tracking/model/session_dto.py
ml_tracking/model/status_update_command.py
ml_tracking/models/__init__.py
ml_tracking/test/__init__.py
ml_tracking/test/test_data_row_dto.py
ml_tracking/test/test_data_row_image_dto.py
ml_tracking/test/test_data_rows_api.py
ml_tracking/test/test_delete_api.py
ml_tracking/test/test_download_api.py
ml_tracking/test/test_entity.py
ml_tracking/test/test_epoch_info.py
ml_tracking/test/test_epoch_info_all_of.py
ml_tracking/test/test_epoch_info_api.py
ml_tracking/test/test_epoch_update_command.py
ml_tracking/test/test_hosted_service_api.py
ml_tracking/test/test_hosted_service_dto.py
ml_tracking/test/test_image_dto.py
ml_tracking/test/test_iteration_update_command.py
ml_tracking/test/test_ml_model_api.py
ml_tracking/test/test_model.py
ml_tracking/test/test_model_all_of.py
ml_tracking_api-1.2.9.dist-info/METADATA
ml_tracking_api-1.2.9.dist-info/WHEEL
ml_tracking_api-1.2.9.dist-info/top_level.txt
ml_tracking_api-1.2.9.dist-info/RECORD
