Metadata-Version: 2.1
Name: ml-tracking-api
Version: 1.2.9
Summary: REST ML-AI API
Home-page: https://github.com/EimantasN/Equusight_BackEnd
Author: Eimantas Noreika
Author-email: noreika.eimantas@gmail.com
License: UNKNOWN
Keywords: OpenAPI,OpenAPI-Generator,REST ML-AI API
Platform: UNKNOWN
Requires-Python: >=3.6
Requires-Dist: urllib3 (>=1.25.3)
Requires-Dist: python-dateutil
